vsbutton/__init__.py
vsbutton-0.5.dist-info/METADATA
vsbutton-0.5.dist-info/WHEEL
vsbutton-0.5.dist-info/license.txt
vsbutton-0.5.dist-info/top_level.txt
vsbutton-0.5.dist-info/RECORD
