Metadata-Version: 2.1
Name: vsbutton
Version: 0.5
Summary: This Package is used to create Buttons like in Visual Studio 2023
Author: Rana Kabeer
License-File: license.txt
